{
  "id": "shared-compendium",
  "title": "Shared compendium",
  "version": "1.0.0",
  "compatibility": {
    "minimum": "12",
    "verified": "12"
  },
  "authors": [
    {
      "name": "Goblin",
      "flags": {}
    }
  ],
  "packs": [
    {
      "name": "monster-hunter-class",
      "label": "Clases Custom",
      "path": "packs/monster-hunter-class",
      "type": "Item",
      "system": "dnd5e",
      "ownership": {
        "PLAYER": "OBSERVER",
        "ASSISTANT": "OWNER"
      }
    }
  ]
}